sprout/__init__.py
sprout/__main__.py
sprout/cli.py
sprout/exceptions.py
sprout/types.py
sprout/utils.py
sprout/commands/__init__.py
sprout/commands/create.py
sprout/commands/ls.py
sprout/commands/path.py
sprout/commands/rm.py
sprout_cli-0.6.0.dist-info/METADATA
sprout_cli-0.6.0.dist-info/WHEEL
sprout_cli-0.6.0.dist-info/entry_points.txt
sprout_cli-0.6.0.dist-info/licenses/LICENSE
sprout_cli-0.6.0.dist-info/RECORD
